ytt/__init__.py
ytt/ytt.py
ytt-1.0.0.dist-info/LICENSE
ytt-1.0.0.dist-info/METADATA
ytt-1.0.0.dist-info/WHEEL
ytt-1.0.0.dist-info/top_level.txt
ytt-1.0.0.dist-info/RECORD
