Metadata-Version: 2.1
Name: ytt
Version: 1.0.0
Summary: Python module for send videos of a Youtube channel to a telegram group , channel or chat
Home-page: https://github.com/nimafanniasl/py_youtube_to_telegram
Author: Nima Fanniasl
Author-email: info@smartnima.com
License: UNKNOWN
Project-URL: Bug Tracker, https://github.com/nimafanniasl/py_youtube_to_telegram/issues
Platform: UNKNOWN
Classifier: Programming Language :: Python :: 3
Classifier: License :: OSI Approved :: GNU General Public License v3 (GPLv3)
Classifier: Operating System :: OS Independent
Requires-Python: >=3.7
License-File: LICENSE
